standard_names/__init__.py
standard_names/states.py
factly-0.0.1.dist-info/METADATA
factly-0.0.1.dist-info/WHEEL
factly-0.0.1.dist-info/top_level.txt
factly-0.0.1.dist-info/RECORD
