Metadata-Version: 2.1
Name: factly
Version: 0.0.1
Summary: A package template
Home-page: https://github.com/
Author: Tharun Paul
Author-email: paul.tharun29@gmail.com
License: : OSI Approved :: MIT License
Platform: UNKNOWN
Classifier: Programming Language :: Python :: 3
Classifier: License :: OSI Approved :: MIT License
Classifier: Operating System :: OS Independent
Requires-Python: >=3.6
